<?xml version="1.0" encoding="utf-8"?>
<stringset>

  <string src="NetStream" id="msg_title_menu_first" />
  <string src="YouTube" id="msg_fpmenu_item_0" />
  <string src="Servidor HTTP" id="msg_fpmenu_item_1" />
  <string src="Servidor FTP" id="msg_fpmenu_item_2" />
  <string src="Armazenamento Local" id="msg_fpmenu_item_3" />

  <string src="Histórico" id="msg_youtube_history" />
  <string src="Descrição" id="msg_youtube_description" />
  <string src="Carregar mais comentários..." id="msg_youtube_comment_more" />
  <string src="Detalhes do Comentário" id="msg_youtube_comment_detail" />
  <string src="Respostas do Comentário" id="msg_youtube_comment_reply" />
  <string src=" gosteis" id="msg_youtube_comment_like_count" />

  <string src="Próxima Página" id="msg_next_page" />
  <string src="Página Anterior" id="msg_previous_page" />

  <string src="Configurações" id="msg_settings" />
  <string src="Servidor HTTP" id="msg_settings_http" />
  <string src="Servidor FTP" id="msg_settings_ftp" />
  <string src="Armazenamento Local" id="msg_settings_local" />
  <string src="Buscar" id="msg_settings_search" />
  <string src="Comentários" id="msg_settings_comment" />
  <string src="Qualidade" id="msg_settings_quality" />
  <string src="Reprodução" id="msg_settings_youtube_player" />
  <string src="Sincronizar na Nuvem" id="msg_settings_cloud_sync" />
  <string src="Informação de Versão" id="msg_settings_verinfo" />
  
  <string src="Endereço IP" id="msg_http_host" />
  <string src="Porta" id="msg_http_port" />
  <string src="Usuário" id="msg_http_user" />
  <string src="Senha" id="msg_http_password" />

  <string src="Endereço IP" id="msg_ftp_host" />
  <string src="Porta" id="msg_ftp_port" />
  <string src="Usuário" id="msg_ftp_user" />
  <string src="Senha" id="msg_ftp_password" />
  <string src="Usar NLST" id="msg_ftp_nlst" />
  <string src="Habilitar essa opção vai fazer o NetStream enviar comandos NLST para o servidor FTP ao invés do comando LIST. Essa opção acaba sendo mais rápida, contudo não é suportada por alguns servidores FTP." id="msg_ftp_nlst_hint" />

  <string src="Prefixo para Playlists .m3u8 Relativas" id="msg_local_playlist_prefix" />
  <string src="Organizar por Nome" id="msg_local_sort_name" />
  <string src="Organizar por Tipo" id="msg_local_sort_type" />
  <string src="Crescente" id="msg_option_local_sort_name_0" />
  <string src="Decresecente" id="msg_option_local_sort_name_1" />
  <string src="Pastas Primeiro" id="msg_option_local_sort_type_0" />
  <string src="Arquivos Primeiro" id="msg_option_local_sort_type_1" />

  <string src="Qualidade de Vídeo Favorita" id="msg_youtube_quality" />
  <string src="Qualidade de Live Favorita" id="msg_youtube_hls_quality" />

  <string src="Instância do Invidious" id="msg_youtube_inv_instance" />
  <string src="Região" id="msg_youtube_region" />
  <string src="Organizar" id="msg_youtube_search_sort" />
  <string src="Data" id="msg_youtube_search_date" />
  <string src="Organizar" id="msg_youtube_comment_sort" />
  
  <string src="Relevância" id="msg_option_search_sort_0" />
  <string src="Classificação" id="msg_option_search_sort_1" />
  <string src="Data" id="msg_option_search_sort_2" />
  <string src="Visualizações" id="msg_option_search_sort_3" />
  
  <string src="Hora" id="msg_option_search_date_0" />
  <string src="Hoje" id="msg_option_search_date_1" />
  <string src="Semana" id="msg_option_search_date_2" />
  <string src="Mês" id="msg_option_search_date_3" />
  <string src="Ano" id="msg_option_search_date_4" />
  <string src="Qualquer" id="msg_option_search_date_5" />
  
  <string src="Relevância" id="msg_option_comment_sort_0" />
  <string src="Novos" id="msg_option_comment_sort_1" />
  
  <string src="360P" id="msg_option_youtube_quality_0" />
  <string src="720P" id="msg_option_youtube_quality_1" />
  
  <string src="144P" id="msg_option_youtube_hls_quality_0" />
  <string src="240P" id="msg_option_youtube_hls_quality_1" />
  <string src="360P" id="msg_option_youtube_hls_quality_2" />
  <string src="480P" id="msg_option_youtube_hls_quality_3" />
  <string src="720P" id="msg_option_youtube_hls_quality_4" />

  <string src="Sincronizar Dados Automaticamente" id="msg_toggle_cloud_sync_auto" />

  <string src="Iniciar Minimizado" id="msg_toggle_youtube_min" />

  <string src="Upload To Cloud" id="msg_settings_youtube_cloud_upload" />
  <string src="Get From Cloud" id="msg_settings_youtube_cloud_download" />
  <string src="Limpar Histórico" id="msg_settings_youtube_clean_history" />
  <string src="Limpar Favoritos" id="msg_settings_youtube_clean_fav" />
  <string src="Todo o histórico de vídeos vai ser apagado! Deseja continuar?" id="msg_settings_youtube_clean_history_confirm" />
  <string src="Todos os favoritos vão ser apagados! Deseja continuar?" id="msg_settings_youtube_clean_fav_confirm" />
  <string src="Baixar" id="msg_settings_youtube_download" />
  <string src="Baixar áudio" id="msg_settings_youtube_download_audio" />
  <string src="O vídeo foi adicionado a fila de Downloads." id="msg_settings_youtube_download_begin" />

  <string src="Ocorreu um erro com a PlayStation™Network. Os dados na Nuvem não vão estar disponíveis. Tenha certeza que você está logado em uma conta da PlayStation™Network." id="msg_error_psn_connection" />
  

</stringset>
